LICENSE
MANIFEST.in
README.md
pyproject.toml
setup.py
src/bindensity/__init__.py
src/bindensity/libbindensity.c
src/bindensity/libbindensity.h
src/bindensity/pywrapbindensity.c
src/bindensity.egg-info/PKG-INFO
src/bindensity.egg-info/SOURCES.txt
src/bindensity.egg-info/dependency_links.txt
src/bindensity.egg-info/requires.txt
src/bindensity.egg-info/top_level.txt