Metadata-Version: 2.4
Name: bindensity
Version: 0.1.4
Summary: Suite of functions to manipulate bins densities and covariance matrices.
Author-email: Jean-Baptiste Delisle <jean-baptiste.delisle@unige.ch>
Project-URL: Homepage, https://gitlab.unige.ch/delisle/bindensity
Project-URL: Issues, https://gitlab.unige.ch/delisle/bindensity/-/issues
Classifier: Programming Language :: Python :: 3
Classifier: License :: OSI Approved :: European Union Public Licence 1.2 (EUPL 1.2)
Classifier: Operating System :: OS Independent
Requires-Python: >=3.9
License-File: LICENSE
Requires-Dist: numpy>=1.19
Dynamic: license-file
